[
	{ "s": "NA", "p": [12, 9, 15, 6, 3, 13] },
	{ "s": "NECESSÁRIOS", "p": [11] },
	{ "s": "NESTA", "p": [11, 14, 3] },
	{ "s": "NESTE", "p": [2, 9, 7, 15, 16, 14, 13, 12, 8, 6, 4, 3] },
	{ "s": "NF", "p": [9] },
	{ "s": "NF-E", "p": [9] },
	{ "s": "NFS", "p": [9] },
	{ "s": "NFS-E", "p": [9] },
	{ "s": "NO", "p": [9, 13, 6, 5, 10, 16, 12, 11, 3, 1] },
	{ "s": "NOME", "p": [13, 12, 10, 9, 6, 5] },
	{ "s": "NOMES", "p": [11] },
	{ "s": "NOS", "p": [9] },
	{ "s": "NOVA", "p": [16, 14, 3] },
	{ "s": "NOVAS", "p": [7] },
	{ "s": "NOVO", "p": [10, 8, 11, 9, 7, 3] },
	{ "s": "NOVOS", "p": [10, 7] },
	{ "s": "NÃO", "p": [6] },
	{ "s": "NÚMERO", "p": [9, 15] },
	{ "s": "NÚMEROS", "p": [6] }
]